Metadata-Version: 1.0
Name: gausbin-probability-distro
Version: 1.2
Summary: Gaussian and Binomial distributions
Home-page: UNKNOWN
Author: Doylee
Author-email: myemail@something.com
License: UNKNOWN
Platform: UNKNOWN
